bitgravityzone/__init__.py
bitgravityzone/client.py
bitgravityzone/exceptions.py
bitgravityzone/models.py
bitgravityzone-0.1.1.dist-info/LICENSE.txt
bitgravityzone-0.1.1.dist-info/METADATA
bitgravityzone-0.1.1.dist-info/WHEEL
bitgravityzone-0.1.1.dist-info/top_level.txt
bitgravityzone-0.1.1.dist-info/RECORD
