Metadata-Version: 2.1
Name: bitgravityzone
Version: 0.1.1
Summary: GravityZone API
Home-page: https://github.com/sonpd2/bitgravityzone
Author: son
Author-email: son@example.com
Classifier: Programming Language :: Python :: 3
Classifier: License :: OSI Approved :: MIT License
Classifier: Operating System :: OS Independent
Requires-Python: >=3.6
License-File: LICENSE.txt
Requires-Dist: httpx>=0.24.0
